nixwrap_index/__init__.py
nixwrap_index/data/.gitkeep
nixwrap_index/data/index-aarch64-linux
nixwrap_index/data/.gitkeep
nixwrap_index/data/index-aarch64-linux
nixwrap_index-2026.2.1.dist-info/METADATA
nixwrap_index-2026.2.1.dist-info/WHEEL
nixwrap_index-2026.2.1.dist-info/RECORD
