Metadata-Version: 2.4
Name: nixwrap-index
Version: 2026.2.1
Summary: Nix-index database for nixwrap
License-Expression: MIT
Requires-Python: >=3.14
